<odoo>
  <data>
    <!--record id="view_product_form" model="ir.ui.view">
            <field name="name">product.ice.form</field>
            <field name="model">product.product</field>
            <field name="inherit_id" ref="product.product_normal_form_view"/>
            <field name="arch" type="xml">
                <xpath expr="//notebook" position="inside">
                  <page string="ICE">
                  <group>
                    <group>
                      <field name="ice_id"/>
                      </group>
                    </group>       
                    </page>             
                </xpath>
            </field>
        </record-->
  </data>
</odoo>